counterpartner/__init__.py
counterpartner/counterpartner.py
counterpartner/match.py
counterpartner-0.10.2.dist-info/LICENSE
counterpartner-0.10.2.dist-info/METADATA
counterpartner-0.10.2.dist-info/WHEEL
counterpartner-0.10.2.dist-info/top_level.txt
counterpartner-0.10.2.dist-info/RECORD
