Metadata-Version: 2.1
Name: counterpartner
Version: 0.10.2
Summary: Counterpartner
Home-page: https://github.com/richardtjornhammar/counterpartner
Author: Richard Tjörnhammar
Author-email: richard.tjornhammar@gmail.com
License: UNKNOWN
Platform: UNKNOWN
Classifier: Programming Language :: Python :: 3
Classifier: License :: OSI Approved :: Apache Software License
Classifier: Operating System :: OS Independent
